msqlpd/__init__.py
msqlpd/src/connection.py
msqlpd-4.0.4.dist-info/LICENSE
msqlpd-4.0.4.dist-info/METADATA
msqlpd-4.0.4.dist-info/WHEEL
msqlpd-4.0.4.dist-info/top_level.txt
msqlpd-4.0.4.dist-info/RECORD
