Metadata-Version: 2.1
Name: msqlpd
Version: 4.0.4
Summary: return a path information
Author: Moses Dastmard
License-File: LICENSE
Requires-Dist: sqlalchemy
Requires-Dist: pandas
Requires-Dist: mysql-connector-python
Requires-Dist: joblib
